rorm/__init__.py
rorm/client.py
rorm/settings.py
rorm/types.py
rorm-0.0.4.dist-info/DESCRIPTION.rst
rorm-0.0.4.dist-info/METADATA
rorm-0.0.4.dist-info/RECORD
rorm-0.0.4.dist-info/WHEEL
rorm-0.0.4.dist-info/metadata.json
rorm-0.0.4.dist-info/top_level.txt
tests/types/__init__.py
tests/types/test_hash.py
tests/types/test_string.py
