Metadata-Version: 2.0
Name: rorm
Version: 0.0.4
Summary: Wraps redis data structures in python objects.
Home-page: https://github.com/nqaegg/rorm.git
Author: Andrzej Mamak
Author-email: andrzej@mamak.eu.org
License: MIT
Keywords: redis development
Platform: UNKNOWN
Classifier: Development Status :: 2 - Pre-Alpha
Classifier: Intended Audience :: Developers
Classifier: Topic :: Software Development :: Libraries :: Python Modules
Classifier: License :: OSI Approved :: MIT License
Classifier: Programming Language :: Python :: 3.4
Classifier: Programming Language :: Python :: 3.5
Requires-Dist: redis
Provides-Extra: dev
Requires-Dist: ipdb; extra == 'dev'
Provides-Extra: test
Requires-Dist: coverage; extra == 'test'
Requires-Dist: factory-boy; extra == 'test'
